aiohttp_aiopylimit/__init__.py
aiohttp_aiopylimit/decorators.py
aiohttp_aiopylimit/limit.py
aiohttp_aiopylimit-1.0.0.dev0.dist-info/LICENSE
aiohttp_aiopylimit-1.0.0.dev0.dist-info/METADATA
aiohttp_aiopylimit-1.0.0.dev0.dist-info/WHEEL
aiohttp_aiopylimit-1.0.0.dev0.dist-info/top_level.txt
aiohttp_aiopylimit-1.0.0.dev0.dist-info/RECORD
